.envrc
AUTHORS
ChangeLog
LICENSE
README.md
setup.cfg
setup.py
shell.nix
nixpkgs/__init__.py
nixpkgs.egg-info/PKG-INFO
nixpkgs.egg-info/SOURCES.txt
nixpkgs.egg-info/dependency_links.txt
nixpkgs.egg-info/not-zip-safe
nixpkgs.egg-info/pbr.json
nixpkgs.egg-info/top_level.txt