Metadata-Version: 1.1
Name: nixpkgs
Version: 0.2.3
Summary: Abuses Nix philosophy, allowing me to do `from nixpkgs import scipy` anytime
Home-page: https://github.com/t184256/nixpkgs-python-importer
Author: Alexander Sosedkin
Author-email: monk@unboiled.info
License: MIT
Keywords: nix
Platform: UNKNOWN
Classifier: Development Status :: 2 - Pre-Alpha
Classifier: Intended Audience :: Developers
Classifier: Intended Audience :: Information Technology
Classifier: License :: OSI Approved :: MIT License
Classifier: Operating System :: OS Independent
Classifier: Programming Language :: Python
Classifier: Programming Language :: Python :: 3 :: Only
